kofnet
