Metadata-Version: 2.1
Name: kofnet
Version: 0.0.3
Summary: Extract SNI bug host for different ISPs based on country
Home-page: https://github.com/Simatwa/kofnet
Author: Smartwa
Author-email: simatwacaleb@proton.me
Maintainer: Smartwa
License: MIT
Project-URL: Bug Report, https://github.com/Simatwa/kofnet/issues/new
Project-URL: Homepage, https://github.com/Simatwa/kofnet
Project-URL: Source Code, https://github.com/Simatwa/kofnet
Project-URL: Issue Tracker, https://github.com/Simatwa/kofnet/issues
Project-URL: Download, https://github.com/Simatwa/kofnet/releases
Project-URL: Documentation, https://github.com/Simatwa/kofnet/blob/main/docs
Keywords: kofnet
Classifier: License :: OSI Approved :: MIT License
Classifier: Intended Audience :: Developers
Classifier: Intended Audience :: Developers
Classifier: Natural Language :: English
Classifier: License :: Free For Home Use
Classifier: Intended Audience :: Customer Service
Classifier: Programming Language :: Python
Classifier: Topic :: Software Development :: Libraries :: Python Modules
Classifier: Programming Language :: Python :: 3 :: Only
Classifier: Programming Language :: Python :: 3.10
Classifier: Programming Language :: Python :: 3.10
Classifier: Programming Language :: Python :: 3.11
Classifier: Programming Language :: Python :: 3.12
Requires-Python: >=3.10
License-File: LICENSE
Requires-Dist: requests>=2.31.0
Provides-Extra: cli
Requires-Dist: click==8.1.3; extra == "cli"
Requires-Dist: tabulate==0.9.0; extra == "cli"
Provides-Extra: all
Requires-Dist: requests>=2.31.0; extra == "all"
Requires-Dist: click==8.1.3; extra == "all"
Requires-Dist: tabulate==0.9.0; extra == "all"
